{
    "info": {
        "title": "Bagpipe",
        "images": {
            "Base": "https://static.wikia.nocookie.net/mrfz/images/0/0d/Bagpipe_Elite_2.png/revision/latest/scale-to-width-down/268?cb=20200318201553",
            "Elite 2": "https://static.wikia.nocookie.net/mrfz/images/7/7f/Bagpipe_Skin_1.png/revision/latest/scale-to-width-down/268?cb=20201214010246"
        }
    },
    "skills": [
        {
            "name": "Swift Strike γ",
            "image": "data:image/gif;base64,R0lGODlhAQABAIABAAAAAP///yH5BAEAAAEALAAAAAABAAEAQAICTAEAOw%3D%3D",
            "types": [
                "Auto Recovery",
                "Manual Trigger",
                "35 sec."
            ],
            "levels": [
                {
                    "level": "1",
                    "effect": "ATK +20%; ASPD +20",
                    "initial_sp": "0",
                    "sp_cost": "45",
                    "duration": "35s"
                },
                {
                    "level": "2",
                    "effect": "ATK +22%; ASPD +20",
                    "initial_sp": "0",
                    "sp_cost": "44",
                    "duration": "35s"
                },
                {
                    "level": "3",
                    "effect": "ATK +24%; ASPD +20",
                    "initial_sp": "0",
                    "sp_cost": "43",
                    "duration": "35s"
                },
                {
                    "level": "4",
                    "effect": "ATK +27%; ASPD +25",
                    "initial_sp": "5",
                    "sp_cost": "42",
                    "duration": "35s"
                },
                {
                    "level": "5",
                    "effect": "ATK +29%; ASPD +25",
                    "initial_sp": "5",
                    "sp_cost": "41",
                    "duration": "35s"
                },
                {
                    "level": "6",
                    "effect": "ATK +31%; ASPD +25",
                    "initial_sp": "5",
                    "sp_cost": "40",
                    "duration": "35s"
                },
                {
                    "level": "7",
                    "effect": "ATK +34%; ASPD +35",
                    "initial_sp": "10",
                    "sp_cost": "39",
                    "duration": "35s"
                },
                {
                    "level": "M1",
                    "effect": "ATK +37%; ASPD +35",
                    "initial_sp": "10",
                    "sp_cost": "38",
                    "duration": "35s"
                },
                {
                    "level": "M2",
                    "effect": "ATK +40%; ASPD +35",
                    "initial_sp": "10",
                    "sp_cost": "37",
                    "duration": "35s"
                },
                {
                    "level": "M3",
                    "effect": "ATK +45%; ASPD +45",
                    "initial_sp": "15",
                    "sp_cost": "35",
                    "duration": "35s"
                }
            ]
        },
        {
            "name": "High-Impact Assault",
            "image": "data:image/gif;base64,R0lGODlhAQABAIABAAAAAP///yH5BAEAAAEALAAAAAABAAEAQAICTAEAOw%3D%3D",
            "types": [
                "Auto Recovery",
                "Auto Trigger"
            ],
            "levels": [
                {
                    "level": "1",
                    "effect": "Increases the ATK of the next attack to 130%, and strikes an additional time\nCan store up to 1 charges",
                    "initial_sp": "0",
                    "sp_cost": "7",
                    "duration": "–"
                },
                {
                    "level": "2",
                    "effect": "Increases the ATK of the next attack to 135%, and strikes an additional time\nCan store up to 1 charges",
                    "initial_sp": "0",
                    "sp_cost": "7",
                    "duration": "–"
                },
                {
                    "level": "3",
                    "effect": "Increases the ATK of the next attack to 140%, and strikes an additional time\nCan store up to 1 charges",
                    "initial_sp": "0",
                    "sp_cost": "7",
                    "duration": "–"
                },
                {
                    "level": "4",
                    "effect": "Increases the ATK of the next attack to 145%, and strikes an additional time\nCan store up to 1 charges",
                    "initial_sp": "0",
                    "sp_cost": "6",
                    "duration": "–"
                },
                {
                    "level": "5",
                    "effect": "Increases the ATK of the next attack to 150%, and strikes an additional time\nCan store up to 1 charges",
                    "initial_sp": "0",
                    "sp_cost": "6",
                    "duration": "–"
                },
                {
                    "level": "6",
                    "effect": "Increases the ATK of the next attack to 155%, and strikes an additional time\nCan store up to 1 charges",
                    "initial_sp": "0",
                    "sp_cost": "6",
                    "duration": "–"
                },
                {
                    "level": "7",
                    "effect": "Increases the ATK of the next attack to 160%, and strikes an additional time\nCan store up to 2 charges",
                    "initial_sp": "0",
                    "sp_cost": "5",
                    "duration": "–"
                },
                {
                    "level": "M1",
                    "effect": "Increases the ATK of the next attack to 170%, and strikes an additional time\nCan store up to 2 charges",
                    "initial_sp": "0",
                    "sp_cost": "5",
                    "duration": "–"
                },
                {
                    "level": "M2",
                    "effect": "Increases the ATK of the next attack to 180%, and strikes an additional time\nCan store up to 3 charges",
                    "initial_sp": "0",
                    "sp_cost": "5",
                    "duration": "–"
                },
                {
                    "level": "M3",
                    "effect": "Increases the ATK of the next attack to 200%, and strikes an additional time\nCan store up to 3 charges",
                    "initial_sp": "0",
                    "sp_cost": "4",
                    "duration": "–"
                }
            ]
        },
        {
            "name": "Locked Breech Burst",
            "image": "data:image/gif;base64,R0lGODlhAQABAIABAAAAAP///yH5BAEAAAEALAAAAAABAAEAQAICTAEAOw%3D%3D",
            "types": [
                "Auto Recovery",
                "Manual Trigger",
                "20 sec."
            ],
            "levels": [
                {
                    "level": "1",
                    "effect": "ATK Interval increases, Block +1, ATK and DEF +30%, and attacks hit 3 times in a row",
                    "initial_sp": "9",
                    "sp_cost": "40",
                    "duration": "20s"
                },
                {
                    "level": "2",
                    "effect": "ATK Interval increases, Block +1, ATK and DEF +40%, and attacks hit 3 times in a row",
                    "initial_sp": "10",
                    "sp_cost": "40",
                    "duration": "20s"
                },
                {
                    "level": "3",
                    "effect": "ATK Interval increases, Block +1, ATK and DEF +50%, and attacks hit 3 times in a row",
                    "initial_sp": "11",
                    "sp_cost": "40",
                    "duration": "20s"
                },
                {
                    "level": "4",
                    "effect": "ATK Interval increases, Block +1, ATK and DEF +60%, and attacks hit 3 times in a row",
                    "initial_sp": "12",
                    "sp_cost": "40",
                    "duration": "20s"
                },
                {
                    "level": "5",
                    "effect": "ATK Interval increases, Block +1, ATK and DEF +70%, and attacks hit 3 times in a row",
                    "initial_sp": "13",
                    "sp_cost": "40",
                    "duration": "20s"
                },
                {
                    "level": "6",
                    "effect": "ATK Interval increases, Block +1, ATK and DEF +80%, and attacks hit 3 times in a row",
                    "initial_sp": "14",
                    "sp_cost": "40",
                    "duration": "20s"
                },
                {
                    "level": "7",
                    "effect": "ATK Interval increases, Block +1, ATK and DEF +90%, and attacks hit 3 times in a row",
                    "initial_sp": "15",
                    "sp_cost": "40",
                    "duration": "20s"
                },
                {
                    "level": "M1",
                    "effect": "ATK Interval increases, Block +1, ATK and DEF +100%, and attacks hit 3 times in a row",
                    "initial_sp": "18",
                    "sp_cost": "40",
                    "duration": "20s"
                },
                {
                    "level": "M2",
                    "effect": "ATK Interval increases, Block +1, ATK and DEF +110%, and attacks hit 3 times in a row",
                    "initial_sp": "21",
                    "sp_cost": "40",
                    "duration": "20s"
                },
                {
                    "level": "M3",
                    "effect": "ATK Interval increases, Block +1, ATK and DEF +120%, and attacks hit 3 times in a row",
                    "initial_sp": "25",
                    "sp_cost": "40",
                    "duration": "20s"
                }
            ]
        }
    ],
    "skill_upgrade_costs": {
        "2": [
            {
                "name": "Skill Summary - 1",
                "quantity": "5"
            }
        ],
        "3": [
            {
                "name": "Skill Summary - 1",
                "quantity": "5"
            },
            {
                "name": "Ester",
                "quantity": "6"
            },
            {
                "name": "Oriron Shard",
                "quantity": "4"
            }
        ],
        "4": [
            {
                "name": "Skill Summary - 2",
                "quantity": "8"
            },
            {
                "name": "Oriron",
                "quantity": "4"
            }
        ],
        "5": [
            {
                "name": "Skill Summary - 2",
                "quantity": "8"
            },
            {
                "name": "Polyketon",
                "quantity": "4"
            },
            {
                "name": "Orirock Cube",
                "quantity": "5"
            }
        ],
        "6": [
            {
                "name": "Skill Summary - 2",
                "quantity": "8"
            },
            {
                "name": "Oriron Cluster",
                "quantity": "6"
            }
        ],
        "7": [
            {
                "name": "Skill Summary - 3",
                "quantity": "8"
            },
            {
                "name": "Loxic Kohl",
                "quantity": "5"
            },
            {
                "name": "Aketon",
                "quantity": "4"
            }
        ]
    },
    "mastery_costs": {
        "Skill1": {
            "masteries": {
                "M1": [
                    {
                        "name": "Skill Summary - 3",
                        "quantity": "8"
                    },
                    {
                        "name": "White Horse Kohl",
                        "quantity": "4"
                    },
                    {
                        "name": "Aketon",
                        "quantity": "8"
                    }
                ],
                "M2": [
                    {
                        "name": "Skill Summary - 3",
                        "quantity": "8"
                    },
                    {
                        "name": "Manganese Trihydrate",
                        "quantity": "4"
                    },
                    {
                        "name": "Integrated Device",
                        "quantity": "4"
                    }
                ],
                "M3": [
                    {
                        "name": "Skill Summary - 3",
                        "quantity": "8"
                    },
                    {
                        "name": "Grindstone Pentahydrate",
                        "quantity": "4"
                    },
                    {
                        "name": "Loxic Kohl",
                        "quantity": "7"
                    }
                ]
            }
        },
        "Skill2": {
            "masteries": {
                "M1": [
                    {
                        "name": "Skill Summary - 3",
                        "quantity": "12"
                    },
                    {
                        "name": "RMA70-24",
                        "quantity": "4"
                    },
                    {
                        "name": "Manganese Trihydrate",
                        "quantity": "7"
                    }
                ],
                "M2": [
                    {
                        "name": "Skill Summary - 3",
                        "quantity": "12"
                    },
                    {
                        "name": "Incandescent Alloy Block",
                        "quantity": "4"
                    },
                    {
                        "name": "RMA70-24",
                        "quantity": "8"
                    }
                ],
                "M3": [
                    {
                        "name": "Skill Summary - 3",
                        "quantity": "12"
                    },
                    {
                        "name": "Polymerized Gel",
                        "quantity": "4"
                    },
                    {
                        "name": "Orirock Concentration",
                        "quantity": "10"
                    }
                ]
            }
        },
        "Skill3": {
            "masteries": {
                "M1": [
                    {
                        "name": "Skill Summary - 3",
                        "quantity": "15"
                    },
                    {
                        "name": "Bipolar Nanoflake",
                        "quantity": "6"
                    },
                    {
                        "name": "Keton Colloid",
                        "quantity": "5"
                    }
                ],
                "M2": [
                    {
                        "name": "Skill Summary - 3",
                        "quantity": "15"
                    },
                    {
                        "name": "D32 Steel",
                        "quantity": "6"
                    },
                    {
                        "name": "White Horse Kohl",
                        "quantity": "7"
                    }
                ],
                "M3": [
                    {
                        "name": "Skill Summary - 3",
                        "quantity": "15"
                    },
                    {
                        "name": "Bipolar Nanoflake",
                        "quantity": "6"
                    },
                    {
                        "name": "Oriron Block",
                        "quantity": "4"
                    }
                ]
            }
        }
    },
    "talents": [
        {
            "name": "Precise Reloading",
            "elite_levels": [
                {
                    "level": "Elite 1",
                    "description": "When attacking, has a 25% chance to increase ATK to 110% and strike an additional target"
                },
                {
                    "level": "Elite 2",
                    "description": "When attacking, has a 25% chance to increase ATK to 130% and strike an additional target"
                }
            ],
            "potential_upgrades": [
                {
                    "level": "Potential 3",
                    "description": "When attacking, has a 28%(+3%) chance to increase ATK to 110% and strike an additional target"
                },
                {
                    "level": "Potential 3",
                    "description": "When attacking, has a 28%(+3%) chance to increase ATK to 130% and strike an additional target"
                }
            ]
        },
        {
            "name": "Military Tradition",
            "elite_levels": [
                {
                    "level": "Elite 2",
                    "description": "When this unit is in the squad, all Vanguards gain +6 Initial SP"
                }
            ],
            "potential_upgrades": [
                {
                    "level": "Potential 5",
                    "description": "When this unit is in the squad, all Vanguards gain +8(+2) Initial SP"
                }
            ]
        }
    ]
}